odoo9_addon_partner_contact_nutrition_activity_level-9.0.1.0.0-py2.7-nspkg.pth
odoo_addons/partner_contact_nutrition_activity_level/__openerp__.py
odoo_addons/partner_contact_nutrition_activity_level/__init__.py
odoo_addons/partner_contact_nutrition_activity_level/README.rst
odoo_addons/partner_contact_nutrition_activity_level/models/res_partner.py
odoo_addons/partner_contact_nutrition_activity_level/models/__init__.py
odoo_addons/partner_contact_nutrition_activity_level/views/res_partner_view.xml
odoo_addons/partner_contact_nutrition_activity_level/static/description/icon.png
odoo9_addon_partner_contact_nutrition_activity_level-9.0.1.0.0.dist-info/top_level.txt
odoo9_addon_partner_contact_nutrition_activity_level-9.0.1.0.0.dist-info/WHEEL
odoo9_addon_partner_contact_nutrition_activity_level-9.0.1.0.0.dist-info/RECORD
odoo9_addon_partner_contact_nutrition_activity_level-9.0.1.0.0.dist-info/metadata.json
odoo9_addon_partner_contact_nutrition_activity_level-9.0.1.0.0.dist-info/DESCRIPTION.rst
odoo9_addon_partner_contact_nutrition_activity_level-9.0.1.0.0.dist-info/METADATA
odoo9_addon_partner_contact_nutrition_activity_level-9.0.1.0.0.dist-info/namespace_packages.txt
